{
  "version": 1,
  "last_updated": "2026-03-12T04:15:32.471110+00:00",
  "pipeline": "market-intel",
  "jobs": {
    "rss-feed-monitor": {
      "last_run": "2026-03-12T04:15:32.471074+00:00",
      "status": "ok",
      "items_found": 109,
      "summary": "109 matches across 20 feeds. Top themes: US & International Top News Stories Today - AP News, At least 17 killed after drone strikes school in Sudan, French aid worker among three killed in dronestrike in east DRC, M23 rebels say",
      "context": {
        "top_keywords": [
          "ev",
          "ai",
          "ukraine",
          "crisis",
          "health",
          "eu",
          "attack",
          "rate"
        ],
        "notable_stories": [
          "US & International Top News Stories Today - AP News",
          "At least 17 killed after drone strikes school in Sudan",
          "French aid worker among three killed in dronestrike in east DRC, M23 rebels say",
          "At least 65 Nigerian soldiers killed in jihadist raids in country\u2019s north-east",
          "Experts fear \u2018unethical\u2019 vaccine trial in Africa is \u2018prototype\u2019 for US studies under RFK Jr",
          "Prison sentences for pair who attacked gay men hailed as sign of hope for Kenya\u2019s LGBTQ+ community",
          "Quit fossil fuels to stem deadly floods in Brazil\u2019s coffee heartland, say scientists",
          "El Salvador\u2019s mass arrest policy may have led to crimes against humanity, study shows",
          "Argentina grants asylum to Bras\u00edlia rioter in move that may sway Brazil vote",
          "Jos\u00e9 Antonio Kast, the Pinochet fan about to swerve Chile to the far right"
        ],
        "enrichment_rate": "10%"
      },
      "last_updated": "2026-03-12T04:15:32.471107+00:00"
    },
    "reddit-monitor": {
      "last_run": "2026-03-12T03:41:41.945221+00:00",
      "status": "ok",
      "items_found": 94,
      "summary": "94 posts after enrichment. Top discussions: Why don't you mind your own business, you scrotum?! (15 upvotes), Up to 3 ships now and oil is pushing $100 again (665 upvotes)",
      "context": {
        "top_posts": [
          "Why don't you mind your own business, you scrotum?! (15 upvotes)",
          "Up to 3 ships now and oil is pushing $100 again (665 upvotes)",
          "IOVA - Game, Set, Match! (18 upvotes)",
          "feels like the market gonna drop (186 upvotes)",
          "Here you go, Mods. Second image shows realized gain over $2,500. We are up 50% Y (0 upvotes)"
        ],
        "correlations_with_rss": [
          "ai: Trending on both RSS + Reddit"
        ]
      },
      "last_updated": "2026-03-12T03:41:41.945249+00:00"
    },
    "market-signal-generator": {
      "last_run": "2026-03-12T03:47:28.779957+00:00",
      "status": "ok",
      "signals_generated": 32,
      "summary": "32 signals generated (0 STRONG BUY, 0 BUY, 0 HOLD). Top categories: macroeconomic=12, sentiment_social=9, corporate=5",
      "context": {
        "by_confidence": {
          "STRONG_BUY": 0,
          "BUY": 0,
          "HOLD": 0,
          "HIGH_confidence": 18
        },
        "by_category": {
          "macroeconomic": 12,
          "financial_credit": 2,
          "geopolitical": 4,
          "sentiment_social": 9,
          "corporate": 5
        },
        "shadow_mode": true,
        "enriched_count": 50
      },
      "last_updated": "2026-03-12T03:47:28.779974+00:00"
    },
    "reasoning-engine": {
      "last_run": "2026-03-08T04:47:40.000000+00:00",
      "status": "ok",
      "signals_enhanced": 32,
      "summary": "32 signals with reasoning scores. 16 STRONG BUY (88/100), 11 BUY, 5 HOLD. Top themes: pandemic preparedness gap, Russia sanctions escalation, Iran conflict oil spike, private credit stress, crypto markets tracking war risk.",
      "context": {
        "by_confidence": {
          "STRONG_BUY": 16,
          "BUY": 11,
          "HOLD": 5
        },
        "top_signals": [
          "NSC pandemic unit disbandment - macro volatility signal (88/100)",
          "COVID-19 'Chinese virus' naming - sentiment/crime risk (88/100)",
          "Russia sanctions escalation - geopolitical risk (88/100)",
          "US Inflation gauges pre-Iran war - rates/fx volatility (88/100)",
          "Private credit woes Larry Fink - financial contagion (88/100)"
        ],
        "historical_patterns": [
          "Oct 2023 Iran-Israel attack: oil spiked 5% intraday, defense +2-4%, airlines down",
          "Feb 2022 peace talk failure: markets cratered, defense +2-4%, wheat/gas risk premium",
          "Jan 2023 JPM miss: regional bank selloff, credit spread widening",
          "Mar 2020 COVID crash: pandemic unit disbandment amplifies future outbreak risk"
        ],
        "predicted_moves": {
          "pandemic_signal": "rates_volatility \u2192 fx_move \u2192 equity_factor_rotation",
          "sanctions_signal": "volatility_spike \u2192 risk_repricing",
          "oil_signal": "defense_rally + airlines_drop + energy_volatility",
          "credit_signal": "financials_volatility \u2192 treasury_bid \u2192 credit_tightening"
        },
        "cross_source_insights": "RSS + Reddit alignment on credit stress elevates confidence in financial sector signals; pandemic-related news from RSS strengthens macro volatility theme"
      },
      "last_updated": "2026-03-08T03:47:45.000000+00:00"
    }
  },
  "alerts": [],
  "requires_attention": []
}