{
  "generated_at": "2026-03-31T23:07:29.984697",
  "sample_size": 11,
  "by_category": {
    "financial_credit": {
      "count": 3,
      "avg_outcome_score": 1.0,
      "bias_points": 5.0
    },
    "macroeconomic": {
      "count": 8,
      "avg_outcome_score": 0.812,
      "bias_points": 3.12
    }
  },
  "by_pattern": {
    "Regional Banking Crisis 2023": {
      "count": 3,
      "avg_outcome_score": 1.0,
      "bias_points": 5.0
    },
    "US Credit Rating Downgrade": {
      "count": 8,
      "avg_outcome_score": 0.812,
      "bias_points": 3.12
    }
  }
}