{
  "last_updated": "2026-03-09",
  "skills": {
    "python": {
      "date": "2026-03-09",
      "level": "novice",
      "score": 65.0,
      "recommendation": "keep-level",
      "dimensions": {
        "control_flow": 20,
        "functions": 20,
        "data_structures": 15,
        "testing_basics": 10,
        "variables_and_types": 0,
        "file_operations": 0
      }
    },
    "blender": {
      "date": "2026-03-09",
      "level": "beginner-intermediate",
      "score": 0.0,
      "recommendation": "keep-level",
      "dimensions": {
        "modeling": 0,
        "timing_and_animation": 0,
        "lighting": 0,
        "materials_and_textures": 0,
        "cleanliness": 0
      }
    }
  }
}